.coveragerc
.mailmap
.testr.conf
AUTHORS
CONTRIBUTING.rst
ChangeLog
HACKING.rst
LICENSE
MANIFEST.in
README.rst
babel.cfg
openstack-common.conf
requirements.txt
setup.cfg
setup.py
test-requirements.txt
tox.ini
doc/source/conf.py
doc/source/contributing.rst
doc/source/index.rst
doc/source/installation.rst
doc/source/readme.rst
doc/source/usage.rst
gearstore/__init__.py
gearstore/client.py
gearstore/cmd.py
gearstore/stocker.py
gearstore.egg-info/PKG-INFO
gearstore.egg-info/SOURCES.txt
gearstore.egg-info/dependency_links.txt
gearstore.egg-info/entry_points.txt
gearstore.egg-info/not-zip-safe
gearstore.egg-info/pbr.json
gearstore.egg-info/requires.txt
gearstore.egg-info/top_level.txt
gearstore/store/__init__.py
gearstore/store/sqla.py
gearstore/store/sqla_models.py
gearstore/tests/__init__.py
gearstore/tests/base.py
gearstore/tests/test_client.py
gearstore/tests/test_stocker.py